bk_report_xlsx/__init__.py
bk_report_xlsx/bk_main.py
bk_report_xlsx-0.0.4.dist-info/METADATA
bk_report_xlsx-0.0.4.dist-info/WHEEL
bk_report_xlsx-0.0.4.dist-info/entry_points.txt
bk_report_xlsx-0.0.4.dist-info/top_level.txt
bk_report_xlsx-0.0.4.dist-info/RECORD
