Metadata-Version: 2.1
Name: bk_report_xlsx
Version: 0.0.4
Summary: bk_report_xlsx
Home-page: 
Author: bk
Author-email: brktmbrt@gmail.com
Classifier: Programming Language :: Python :: 3
Classifier: License :: OSI Approved :: MIT License
Classifier: Operating System :: OS Independent
Requires-Python: >=3.6
Requires-Dist: numpy
Requires-Dist: openpyxl
